supervisor_pydantic/__init__.py
supervisor_pydantic/exceptions.py
supervisor_pydantic/utils.py
supervisor_pydantic/client/__init__.py
supervisor_pydantic/client/xmlrpc.py
supervisor_pydantic/config/__init__.py
supervisor_pydantic/config/base.py
supervisor_pydantic/config/convenience.py
supervisor_pydantic/config/eventlistener.py
supervisor_pydantic/config/fcgiprogram.py
supervisor_pydantic/config/group.py
supervisor_pydantic/config/include.py
supervisor_pydantic/config/inet_http_server.py
supervisor_pydantic/config/program.py
supervisor_pydantic/config/rpcinterface.py
supervisor_pydantic/config/supervisor.py
supervisor_pydantic/config/supervisorctl.py
supervisor_pydantic/config/supervisord.py
supervisor_pydantic/config/unix_http_server.py
supervisor_pydantic/config/hydra/base.yaml
supervisor_pydantic/config/hydra/eventlistener/default.yaml
supervisor_pydantic/config/hydra/fcgiprogram/default.yaml
supervisor_pydantic/config/hydra/group/default.yaml
supervisor_pydantic/config/hydra/hydra/hydra_logging/custom.yaml
supervisor_pydantic/config/hydra/hydra/job_logging/custom.yaml
supervisor_pydantic/config/hydra/include/default.yaml
supervisor_pydantic/config/hydra/inet_http_server/default.yaml
supervisor_pydantic/config/hydra/program/default.yaml
supervisor_pydantic/config/hydra/rpcinterface/default.yaml
supervisor_pydantic/config/hydra/supervisorctl/default.yaml
supervisor_pydantic/config/hydra/supervisord/default.yaml
supervisor_pydantic/config/hydra/unix_http_server/default.yaml
supervisor_pydantic/config/utils/__init__.py
supervisor_pydantic/config/utils/relativedelta.py
supervisor_pydantic/convenience/__init__.py
supervisor_pydantic/convenience/__main__.py
supervisor_pydantic/convenience/commands.py
supervisor_pydantic/convenience/common.py
supervisor_pydantic/tests/conftest.py
supervisor_pydantic/tests/gen_test_pydantic.py
supervisor_pydantic/tests/helpers.py
supervisor_pydantic/tests/test_all.py
supervisor_pydantic/tests/test_nolocal.py
supervisor_pydantic-1.3.1.dist-info/METADATA
supervisor_pydantic-1.3.1.dist-info/WHEEL
supervisor_pydantic-1.3.1.dist-info/entry_points.txt
supervisor_pydantic-1.3.1.dist-info/licenses/LICENSE
supervisor_pydantic-1.3.1.dist-info/RECORD
